romonepali/__init__.py
romonepali/uni.py
romonepali-0.0.3.dist-info/DESCRIPTION.rst
romonepali-0.0.3.dist-info/METADATA
romonepali-0.0.3.dist-info/RECORD
romonepali-0.0.3.dist-info/WHEEL
romonepali-0.0.3.dist-info/entry_points.txt
romonepali-0.0.3.dist-info/metadata.json
romonepali-0.0.3.dist-info/top_level.txt
