Metadata-Version: 2.0
Name: romonepali
Version: 0.0.3
Summary: Romonised nepali input method for LInux.
Home-page: https://github.com/psuzn/romoNepali
Author: Sujan Poudel
Author-email: spoudel347@gmail.com
License: MIT
Download-URL: https://github.com/psuzn/romoNepali
Keywords: unicode,Nepali,Romonised,Nepal
Platform: UNKNOWN
Classifier: Environment :: Console
Classifier: Intended Audience :: Information Technology
Classifier: License :: OSI Approved :: MIT License
Classifier: Operating System :: OS Independent
Classifier: Programming Language :: Python
Classifier: Programming Language :: Python :: 3
Requires-Dist: pynput
Requires-Dist: requests
